Metadata-Version: 1.0
Name: i18nize
Version: 0.0.3
Summary: This is a simple Client that integrates with the localization service www.i18nize.com
Home-page: https://github.com/iktw/i18nize
Author: Mohammed Hammoud
Author-email: mohammed@iktw.se
License: MIT licence, see LICENCE.txt
Platform: UNKNOWN
